tiffslide/__init__.py
tiffslide/_compat.py
tiffslide/_kerchunk.py
tiffslide/_types.py
tiffslide/_version.py
tiffslide/_zarr.py
tiffslide/deepzoom.py
tiffslide/py.typed
tiffslide/repair.py
tiffslide/tiffslide.py
tiffslide-2.5.1.dist-info/licenses/LICENSE
tiffslide-2.5.1.dist-info/METADATA
tiffslide-2.5.1.dist-info/WHEEL
tiffslide-2.5.1.dist-info/top_level.txt
tiffslide-2.5.1.dist-info/RECORD
