Metadata-Version: 2.4
Name: tiffslide
Version: 2.5.1
Summary: tifffile-based drop-in replacement for openslide-python
Author-email: Andreas Poehlmann <andreas.poehlmann@bayer.com>
License: New BSD License
Project-URL: Homepage, https://github.com/Bayer-Group/tiffslide
Project-URL: Download, https://github.com/Bayer-Group/tiffslide
Project-URL: Source, https://github.com/Bayer-Group/tiffslide
Project-URL: Changelog, https://github.com/Bayer-Group/tiffslide/blob/main/CHANGELOG.md
Classifier: Development Status :: 3 - Alpha
Classifier: Intended Audience :: Science/Research
Classifier: License :: OSI Approved :: BSD License
Classifier: Programming Language :: Python
Classifier: Programming Language :: Python :: 3 :: Only
Classifier: Programming Language :: Python :: 3.9
Classifier: Programming Language :: Python :: 3.10
Classifier: Programming Language :: Python :: 3.11
Classifier: Programming Language :: Python :: 3.12
Classifier: Programming Language :: Python :: 3.13
Classifier: Topic :: Scientific/Engineering
Classifier: Topic :: Scientific/Engineering :: Information Analysis
Classifier: Topic :: Scientific/Engineering :: Bio-Informatics
Classifier: Topic :: Utilities
Classifier: Operating System :: Microsoft :: Windows
Classifier: Operating System :: POSIX
Classifier: Operating System :: Unix
Classifier: Operating System :: MacOS
Requires-Python: >=3.9
License-File: LICENSE
Requires-Dist: imagecodecs
Requires-Dist: fsspec>=2023.3.0
Requires-Dist: pillow>=9.1.0
Requires-Dist: tifffile<2025.5.21,>=2023.7.4
Requires-Dist: zarr<3.0,>=2.16.0
Requires-Dist: typing_extensions>=4.0
Provides-Extra: dev
Requires-Dist: pre-commit; extra == "dev"
Requires-Dist: black; extra == "dev"
Requires-Dist: pytest>=6; extra == "dev"
Requires-Dist: pytest-benchmark; extra == "dev"
Requires-Dist: pytest-cov; extra == "dev"
Requires-Dist: mypy; extra == "dev"
Dynamic: license-file
